[
    {
        "href": "https://www.amazon.co.jp/-/en/gp/product/B09FLTSQL3?storeType=ebooks&pf_rd_p=f6d8d5b2-da73-4102-80de-af87cf5806e1&pf_rd_r=GCE0KT4DB8R2RAB8EM10&pd_rd_wg=YhrFP&pd_rd_i=B09FLTSQL3&ref_=dbs_r_recs_hcko_kdd_r_0&pd_rd_w=M1gpu&content-id=amzn1.sym.f6d8d5b2-da73-4102-80de-af87cf5806e1&pd_rd_r=8b67cefe-bf14-4ac5-9d58-874d2562a1ca",
        "title": "改訂４版　メンタルヘルス・マネジメント®検定試験II種(ラインケアコース)重要ポイント&問題集",
        "thumbnail": "https://m.media-amazon.com/images/I/51ptukwpGRL._SY300_.jpg"
    },
    {
        "href": "https://www.amazon.co.jp/-/en/gp/product/B09C89HZRV?storeType=ebooks&pf_rd_p=f6d8d5b2-da73-4102-80de-af87cf5806e1&pf_rd_r=GCE0KT4DB8R2RAB8EM10&pd_rd_wg=YhrFP&pd_rd_i=B09C89HZRV&ref_=dbs_r_recs_hcko_kdd_r_1&pd_rd_w=M1gpu&content-id=amzn1.sym.f6d8d5b2-da73-4102-80de-af87cf5806e1&pd_rd_r=8b67cefe-bf14-4ac5-9d58-874d2562a1ca",
        "title": "Ｐｙｔｈｏｎで学ぶ実験計画法入門　ベイズ最適化によるデータ解析 (ＫＳ情報科学専門書)",
        "thumbnail": "https://m.media-amazon.com/images/I/51LVSaAd3+L._SY300_.jpg"
    },
    {
        "href": "https://www.amazon.co.jp/-/en/gp/product/B0BKZWMD6Q?storeType=ebooks&pf_rd_p=f6d8d5b2-da73-4102-80de-af87cf5806e1&pf_rd_r=GCE0KT4DB8R2RAB8EM10&pd_rd_wg=YhrFP&pd_rd_i=B0BKZWMD6Q&ref_=dbs_r_recs_hcko_kdd_r_2&pd_rd_w=M1gpu&content-id=amzn1.sym.f6d8d5b2-da73-4102-80de-af87cf5806e1&pd_rd_r=8b67cefe-bf14-4ac5-9d58-874d2562a1ca",
        "title": "無理をしなくても　内臓脂肪がみるみる落ちる食べ方大全",
        "thumbnail": "https://m.media-amazon.com/images/I/51220Ndd4zL._PJku-sticker-v7,TopRight,0,-50._SY300_.jpg"
    }
]