[
    {
        "href": "https://www.amazon.co.jp/gp/product/B0B4ZQ7PYL?storeType=ebooks&pf_rd_p=7cef433f-789f-4bf6-bc14-7930610f4554&pf_rd_r=KFV7FY25BVN9JCKN40SA&pd_rd_wg=JQ7HA&pd_rd_i=B0B4ZQ7PYL&ref_=dbs_r_recs_hcko_kdd_r_0&pd_rd_w=Npih4&content-id=amzn1.sym.7cef433f-789f-4bf6-bc14-7930610f4554&pd_rd_r=fedc9ea8-23d6-445a-93b0-73561893ef64",
        "title": "結局、腸が9割 名医が教える「腸」最強の健康法",
        "thumbnail": "https://m.media-amazon.com/images/I/518rH3YkE1L._SY300_.jpg"
    },
    {
        "href": "https://www.amazon.co.jp/gp/product/B07WV3TVSB?storeType=ebooks&pf_rd_p=7cef433f-789f-4bf6-bc14-7930610f4554&pf_rd_r=KFV7FY25BVN9JCKN40SA&pd_rd_wg=JQ7HA&pd_rd_i=B07WV3TVSB&ref_=dbs_r_recs_hcko_kdd_r_1&pd_rd_w=Npih4&content-id=amzn1.sym.7cef433f-789f-4bf6-bc14-7930610f4554&pd_rd_r=fedc9ea8-23d6-445a-93b0-73561893ef64",
        "title": "眠れなくなるほど面白い 図解 体脂肪の話",
        "thumbnail": "https://m.media-amazon.com/images/I/516Uokt+UsL._SY300_.jpg"
    },
    {
        "href": "https://www.amazon.co.jp/gp/product/B08W8DDQ7G?storeType=ebooks&pf_rd_p=7cef433f-789f-4bf6-bc14-7930610f4554&pf_rd_r=KFV7FY25BVN9JCKN40SA&pd_rd_wg=JQ7HA&pd_rd_i=B08W8DDQ7G&ref_=dbs_r_recs_hcko_kdd_r_2&pd_rd_w=Npih4&content-id=amzn1.sym.7cef433f-789f-4bf6-bc14-7930610f4554&pd_rd_r=fedc9ea8-23d6-445a-93b0-73561893ef64",
        "title": "難しいことはわかりませんが、マンガで英語が話せる方法を教えてください！",
        "thumbnail": "https://m.media-amazon.com/images/I/51FKJLbCgSL._PJku-sticker-v7,TopRight,0,-50._SY300_.jpg"
    }
]