[
    {
        "href": "https://www.amazon.co.jp/gp/product/B0BZP3T7L5?storeType=ebooks&pf_rd_p=7cef433f-789f-4bf6-bc14-7930610f4554&pf_rd_r=VNFF2QQRJNGXH8MD1QDH&pd_rd_wg=m5uNv&pd_rd_i=B0BZP3T7L5&ref_=dbs_r_recs_hcko_kdd_r_0&pd_rd_w=wMXcg&content-id=amzn1.sym.7cef433f-789f-4bf6-bc14-7930610f4554&pd_rd_r=f329d6f9-fcb9-4dc5-9657-c3b842dee079",
        "title": "朝イチの「ひとり時間」が人生を変える",
        "thumbnail": "https://m.media-amazon.com/images/I/41mOxkF6puL._SY300_.jpg"
    },
    {
        "href": "https://www.amazon.co.jp/gp/product/B0BGMYQD3N?storeType=ebooks&pf_rd_p=7cef433f-789f-4bf6-bc14-7930610f4554&pf_rd_r=VNFF2QQRJNGXH8MD1QDH&pd_rd_wg=m5uNv&pd_rd_i=B0BGMYQD3N&ref_=dbs_r_recs_hcko_kdd_r_1&pd_rd_w=wMXcg&content-id=amzn1.sym.7cef433f-789f-4bf6-bc14-7930610f4554&pd_rd_r=f329d6f9-fcb9-4dc5-9657-c3b842dee079",
        "title": "W24 日本の凄い神木 全都道府県250柱のヌシとそれを守る人に会いに行く (地球の歩き方W)",
        "thumbnail": "https://m.media-amazon.com/images/I/61RssSYeKzL._SY300_.jpg"
    },
    {
        "href": "https://www.amazon.co.jp/gp/product/B08JYX8MH6?storeType=ebooks&pf_rd_p=7cef433f-789f-4bf6-bc14-7930610f4554&pf_rd_r=VNFF2QQRJNGXH8MD1QDH&pd_rd_wg=m5uNv&pd_rd_i=B08JYX8MH6&ref_=dbs_r_recs_hcko_kdd_r_2&pd_rd_w=wMXcg&content-id=amzn1.sym.7cef433f-789f-4bf6-bc14-7930610f4554&pd_rd_r=f329d6f9-fcb9-4dc5-9657-c3b842dee079",
        "title": "事例で学ぶ BtoBマーケティングの戦略と実践",
        "thumbnail": "https://m.media-amazon.com/images/I/51MmbUhNyaL._SY300_.jpg"
    }
]