[
    {
        "href": "https://www.amazon.co.jp/gp/product/B0CCNC2KJC?storeType=ebooks&pf_rd_p=7cef433f-789f-4bf6-bc14-7930610f4554&pf_rd_r=12W1EXDJG2RSAMW14QEN&pd_rd_wg=U4WhI&pd_rd_i=B0CCNC2KJC&ref_=dbs_r_recs_hcko_kdd_r_0&pd_rd_w=7RQZQ&content-id=amzn1.sym.7cef433f-789f-4bf6-bc14-7930610f4554&pd_rd_r=9bed2cca-36ee-499c-a064-5503e5a53261",
        "title": "博士が解いた人付き合いの「トリセツ」",
        "thumbnail": "https://m.media-amazon.com/images/I/51B8daVsn4L._SY300_.jpg"
    },
    {
        "href": "https://www.amazon.co.jp/gp/product/B0C33BYPB4?storeType=ebooks&pf_rd_p=7cef433f-789f-4bf6-bc14-7930610f4554&pf_rd_r=12W1EXDJG2RSAMW14QEN&pd_rd_wg=U4WhI&pd_rd_i=B0C33BYPB4&ref_=dbs_r_recs_hcko_kdd_r_1&pd_rd_w=7RQZQ&content-id=amzn1.sym.7cef433f-789f-4bf6-bc14-7930610f4554&pd_rd_r=9bed2cca-36ee-499c-a064-5503e5a53261",
        "title": "つくりたくなる日々レシピ【Amazon.co.jp限定特典付】",
        "thumbnail": "https://m.media-amazon.com/images/I/41tlaq7zw+L._SY300_.jpg"
    },
    {
        "href": "https://www.amazon.co.jp/gp/product/B0CKHH1BGR?storeType=ebooks&pf_rd_p=7cef433f-789f-4bf6-bc14-7930610f4554&pf_rd_r=12W1EXDJG2RSAMW14QEN&pd_rd_wg=U4WhI&pd_rd_i=B0CKHH1BGR&ref_=dbs_r_recs_hcko_kdd_r_2&pd_rd_w=7RQZQ&content-id=amzn1.sym.7cef433f-789f-4bf6-bc14-7930610f4554&pd_rd_r=9bed2cca-36ee-499c-a064-5503e5a53261",
        "title": "ゼロから始める 繁盛店のつくり方――新しい分野で成果をつくり出すことができた理由",
        "thumbnail": "https://m.media-amazon.com/images/I/51Rvah6VFvL._SY300_.jpg"
    }
]