[
    {
        "href": "https://www.amazon.co.jp/-/en/gp/product/B095P41VYR?storeType=ebooks&pf_rd_t=&pd_rd_i=B095P41VYR&content-id=amzn1.sym.72b6d7f6-bcb1-4aee-8562-cdff945c8c14&pageType=STOREFRONT&pf_rd_p=72b6d7f6-bcb1-4aee-8562-cdff945c8c14&pf_rd_r=WP5N9K99DFRJ9AAR0HGE&pd_rd_wg=DNXgs&pf_rd_s=merchandised-search-11&ref_=dbs_f_r_shv_hcko_kdd_e22eff8d-f530-45e0-9860-4ea881aaffea_0&pd_rd_w=4N8x5&pf_rd_i=3251934051&pd_rd_r=8dca4648-9ae3-4fb5-901e-e42d9dff8b3c",
        "title": "超リテラシー大全",
        "thumbnail": "https://m.media-amazon.com/images/I/51zejOwpTJS._SY375_.jpg"
    },
    {
        "href": "https://www.amazon.co.jp/-/en/gp/product/B09YDBNW11?storeType=ebooks&pf_rd_t=&pd_rd_i=B09YDBNW11&content-id=amzn1.sym.72b6d7f6-bcb1-4aee-8562-cdff945c8c14&pageType=STOREFRONT&pf_rd_p=72b6d7f6-bcb1-4aee-8562-cdff945c8c14&pf_rd_r=WP5N9K99DFRJ9AAR0HGE&pd_rd_wg=DNXgs&pf_rd_s=merchandised-search-11&ref_=dbs_f_r_shv_hcko_kdd_e22eff8d-f530-45e0-9860-4ea881aaffea_1&pd_rd_w=4N8x5&pf_rd_i=3251934051&pd_rd_r=8dca4648-9ae3-4fb5-901e-e42d9dff8b3c",
        "title": "人生はごちそう――自分の身に起こることはすべて栄養ね！",
        "thumbnail": "https://m.media-amazon.com/images/I/51Wx2UUZNvL._SY375_.jpg"
    },
    {
        "href": "https://www.amazon.co.jp/-/en/gp/product/B08Z7H5DL1?storeType=ebooks&pf_rd_t=&pd_rd_i=B08Z7H5DL1&content-id=amzn1.sym.72b6d7f6-bcb1-4aee-8562-cdff945c8c14&pageType=STOREFRONT&pf_rd_p=72b6d7f6-bcb1-4aee-8562-cdff945c8c14&pf_rd_r=WP5N9K99DFRJ9AAR0HGE&pd_rd_wg=DNXgs&pf_rd_s=merchandised-search-11&ref_=dbs_f_r_shv_hcko_kdd_e22eff8d-f530-45e0-9860-4ea881aaffea_2&pd_rd_w=4N8x5&pf_rd_i=3251934051&pd_rd_r=8dca4648-9ae3-4fb5-901e-e42d9dff8b3c",
        "title": "眠れなくなるほど面白い 図解 ストレスの話",
        "thumbnail": "https://m.media-amazon.com/images/I/51-YHKt5raS._SY375_.jpg"
    }
]