[
    {
        "href": "https://www.amazon.co.jp/-/en/gp/product/B07PCPH8SY?storeType=ebooks&pageType=STOREFRONT&pf_rd_p=3a53cad5-13a5-4e53-aff7-185e9992987e&pf_rd_r=E9J063ZN2RZ1JXWHYD0G&pf_rd_s=merchandised-search-6&pf_rd_t=&ref_=dbs_f_r_shv_3a53cad5-13a5-4e53-aff7-185e9992987e_0&pf_rd_i=3251934051",
        "title": "武器としての会計ファイナンス　「カネの流れ」をどう最適化して戦略を成功させるか？",
        "thumbnail": "https://m.media-amazon.com/images/I/51rodsN8eWL._SY300_.jpg"
    },
    {
        "href": "https://www.amazon.co.jp/-/en/gp/product/B073RGXC8L?storeType=ebooks&pageType=STOREFRONT&pf_rd_p=3a53cad5-13a5-4e53-aff7-185e9992987e&pf_rd_r=E9J063ZN2RZ1JXWHYD0G&pf_rd_s=merchandised-search-6&pf_rd_t=&ref_=dbs_f_r_shv_3a53cad5-13a5-4e53-aff7-185e9992987e_1&pf_rd_i=3251934051",
        "title": "トム・ピーターズのサラリーマン大逆襲作戦<１>　ブランド人になれ！",
        "thumbnail": "https://m.media-amazon.com/images/I/51v7FYIc7DL._SY300_.jpg"
    },
    {
        "href": "https://www.amazon.co.jp/-/en/gp/product/B0178FVSUA?storeType=ebooks&pageType=STOREFRONT&pf_rd_p=3a53cad5-13a5-4e53-aff7-185e9992987e&pf_rd_r=E9J063ZN2RZ1JXWHYD0G&pf_rd_s=merchandised-search-6&pf_rd_t=&ref_=dbs_f_r_shv_3a53cad5-13a5-4e53-aff7-185e9992987e_2&pf_rd_i=3251934051",
        "title": "京都・瓢亭　四季の日本料理",
        "thumbnail": "https://m.media-amazon.com/images/I/41U8FB8PvlL._SY300_.jpg"
    }
]