[
    {
        "href": "https://www.amazon.co.jp/-/en/gp/product/B01HD2TN8M?storeType=ebooks&pageType=STOREFRONT&pf_rd_p=166f1c97-f33f-4cff-ad9b-ba61230cf2b3&pf_rd_r=35M8HAWNWMZTJSQ77ZFX&pf_rd_s=merchandised-search-6&pf_rd_t=&ref_=dbs_f_r_shv_166f1c97-f33f-4cff-ad9b-ba61230cf2b3_0&pf_rd_i=3251934051",
        "title": "金利を見れば投資はうまくいく",
        "thumbnail": "https://m.media-amazon.com/images/I/51BQU3Nf9AL._PJku-sticker-v7,TopRight,0,-50._SY300_.jpg"
    },
    {
        "href": "https://www.amazon.co.jp/-/en/gp/product/B08VN6TSXT?storeType=ebooks&pageType=STOREFRONT&pf_rd_p=166f1c97-f33f-4cff-ad9b-ba61230cf2b3&pf_rd_r=35M8HAWNWMZTJSQ77ZFX&pf_rd_s=merchandised-search-6&pf_rd_t=&ref_=dbs_f_r_shv_166f1c97-f33f-4cff-ad9b-ba61230cf2b3_1&pf_rd_i=3251934051",
        "title": "ひきこもり図書館　部屋から出られない人のための１２の物語",
        "thumbnail": "https://m.media-amazon.com/images/I/51R48Bii2+L._SY300_.jpg"
    },
    {
        "href": "https://www.amazon.co.jp/-/en/gp/product/B00KO4YESG?storeType=ebooks&pageType=STOREFRONT&pf_rd_p=166f1c97-f33f-4cff-ad9b-ba61230cf2b3&pf_rd_r=35M8HAWNWMZTJSQ77ZFX&pf_rd_s=merchandised-search-6&pf_rd_t=&ref_=dbs_f_r_shv_166f1c97-f33f-4cff-ad9b-ba61230cf2b3_2&pf_rd_i=3251934051",
        "title": "ＮＨＫ「１００分ｄｅ名著」ブックス　アインシュタイン　相対性理論",
        "thumbnail": "https://m.media-amazon.com/images/I/41SZKAeQ-mL._SY300_.jpg"
    }
]