[
    {
        "href": "https://www.amazon.co.jp/gp/product/B0BVF4BV51?storeType=ebooks&pf_rd_p=f6d8d5b2-da73-4102-80de-af87cf5806e1&pf_rd_r=ZCMAWHHWKA4N8KYQHPDG&pd_rd_wg=u0LBX&pd_rd_i=B0BVF4BV51&ref_=dbs_r_recs_hcko_kdd_r_0&pd_rd_w=YKriP&content-id=amzn1.sym.f6d8d5b2-da73-4102-80de-af87cf5806e1&pd_rd_r=027e04ae-48a9-4cea-8fa0-5c453d38df83",
        "title": "ズボラ母さんのゆる貯め節約術 (扶桑社コミックス)",
        "thumbnail": "https://m.media-amazon.com/images/I/51zIvtfJ5WL._SY300_.jpg"
    },
    {
        "href": "https://www.amazon.co.jp/gp/product/B075127VMJ?storeType=ebooks&pf_rd_p=f6d8d5b2-da73-4102-80de-af87cf5806e1&pf_rd_r=ZCMAWHHWKA4N8KYQHPDG&pd_rd_wg=u0LBX&pd_rd_i=B075127VMJ&ref_=dbs_r_recs_hcko_kdd_r_1&pd_rd_w=YKriP&content-id=amzn1.sym.f6d8d5b2-da73-4102-80de-af87cf5806e1&pd_rd_r=027e04ae-48a9-4cea-8fa0-5c453d38df83",
        "title": "睡眠の科学・改訂新版　なぜ眠るのか　なぜ目覚めるのか (ブルーバックス)",
        "thumbnail": "https://m.media-amazon.com/images/I/411cikcl5WL._SY300_.jpg"
    },
    {
        "href": "https://www.amazon.co.jp/gp/product/B09QQ2LSLV?storeType=ebooks&pf_rd_p=f6d8d5b2-da73-4102-80de-af87cf5806e1&pf_rd_r=ZCMAWHHWKA4N8KYQHPDG&pd_rd_wg=u0LBX&pd_rd_i=B09QQ2LSLV&ref_=dbs_r_recs_hcko_kdd_r_2&pd_rd_w=YKriP&content-id=amzn1.sym.f6d8d5b2-da73-4102-80de-af87cf5806e1&pd_rd_r=027e04ae-48a9-4cea-8fa0-5c453d38df83",
        "title": "【マンガでわかるアウトプット大全】もしも社畜ゾンビが『アウトプット大全』を読んだら",
        "thumbnail": "https://m.media-amazon.com/images/I/511MGZyZdBL._SY300_.jpg"
    }
]