[
    {
        "href": "https://www.amazon.co.jp/gp/product/B08Y8SVLZ8?storeType=ebooks&pf_rd_p=278629a4-108d-466d-8c1f-b029777318e7&pf_rd_r=N1GAYZZ833HPHYVNB7AH&pd_rd_wg=GiVUe&pd_rd_i=B08Y8SVLZ8&ref_=dbs_r_recs_hcko_kmd_r_0&pd_rd_w=T30BE&content-id=amzn1.sym.278629a4-108d-466d-8c1f-b029777318e7&pd_rd_r=315b4212-0c7d-45e9-a66e-1916b6a3ad4a",
        "title": "僕のかわいい娘は双子の賢者 ～特技がデバフの底辺黒魔導士、育てた双子の娘がＳランクの大賢者になってしまう～ (2)",
        "thumbnail": "https://m.media-amazon.com/images/I/51HnmCU7dfL._PJku-sticker-v7,TopRight,0,-50._SY300_.jpg"
    },
    {
        "href": "https://www.amazon.co.jp/gp/product/B0CG9957GK?storeType=ebooks&pf_rd_p=278629a4-108d-466d-8c1f-b029777318e7&pf_rd_r=N1GAYZZ833HPHYVNB7AH&pd_rd_wg=GiVUe&pd_rd_i=B0CG9957GK&ref_=dbs_r_recs_hcko_kmd_r_1&pd_rd_w=T30BE&content-id=amzn1.sym.278629a4-108d-466d-8c1f-b029777318e7&pd_rd_r=315b4212-0c7d-45e9-a66e-1916b6a3ad4a",
        "title": "基礎からの新しいストレージ入門 基本技術から設計・運用管理の実践まで",
        "thumbnail": "https://m.media-amazon.com/images/I/51QE9xrFvJL._SY300_.jpg"
    },
    {
        "href": "https://www.amazon.co.jp/gp/product/B0749JLTS7?storeType=ebooks&pf_rd_p=278629a4-108d-466d-8c1f-b029777318e7&pf_rd_r=N1GAYZZ833HPHYVNB7AH&pd_rd_wg=GiVUe&pd_rd_i=B0749JLTS7&ref_=dbs_r_recs_hcko_kmd_r_2&pd_rd_w=T30BE&content-id=amzn1.sym.278629a4-108d-466d-8c1f-b029777318e7&pd_rd_r=315b4212-0c7d-45e9-a66e-1916b6a3ad4a",
        "title": "どこの家にも怖いものはいる (中公文庫)",
        "thumbnail": "https://m.media-amazon.com/images/I/51ABw6xT9eL._SY300_.jpg"
    },
    {
        "href": "https://www.amazon.co.jp/gp/product/B0C61BNTW9?storeType=ebooks&pf_rd_p=278629a4-108d-466d-8c1f-b029777318e7&pf_rd_r=N1GAYZZ833HPHYVNB7AH&pd_rd_wg=GiVUe&pd_rd_i=B0C61BNTW9&ref_=dbs_r_recs_hcko_kmd_r_3&pd_rd_w=T30BE&content-id=amzn1.sym.278629a4-108d-466d-8c1f-b029777318e7&pd_rd_r=315b4212-0c7d-45e9-a66e-1916b6a3ad4a",
        "title": "システム設計の面接試験",
        "thumbnail": "https://m.media-amazon.com/images/I/51SiQLp2ZgL._SY300_.jpg"
    },
    {
        "href": "https://www.amazon.co.jp/gp/product/B09CGXHFCJ?storeType=ebooks&pf_rd_p=278629a4-108d-466d-8c1f-b029777318e7&pf_rd_r=N1GAYZZ833HPHYVNB7AH&pd_rd_wg=GiVUe&pd_rd_i=B09CGXHFCJ&ref_=dbs_r_recs_hcko_kmd_r_4&pd_rd_w=T30BE&content-id=amzn1.sym.278629a4-108d-466d-8c1f-b029777318e7&pd_rd_r=315b4212-0c7d-45e9-a66e-1916b6a3ad4a",
        "title": "三千円の使いかた (中公文庫)",
        "thumbnail": "https://m.media-amazon.com/images/I/51dsll375bL._SY300_.jpg"
    },
    {
        "href": "https://www.amazon.co.jp/gp/product/B0D2R6L1R8?storeType=ebooks&pf_rd_p=278629a4-108d-466d-8c1f-b029777318e7&pf_rd_r=N1GAYZZ833HPHYVNB7AH&pd_rd_wg=GiVUe&pd_rd_i=B0D2R6L1R8&ref_=dbs_r_recs_hcko_kmd_r_5&pd_rd_w=T30BE&content-id=amzn1.sym.278629a4-108d-466d-8c1f-b029777318e7&pd_rd_r=315b4212-0c7d-45e9-a66e-1916b6a3ad4a",
        "title": "Excelパワークエリ実戦のための技術データの取得、行・列操作によるデータ処理から、モデリング、let式、DAXクエリまで完全解説！",
        "thumbnail": "https://m.media-amazon.com/images/I/51yCO6exn7L._SY300_.jpg"
    },
    {
        "href": "https://www.amazon.co.jp/gp/product/B0CW1HYDD3?storeType=ebooks&pf_rd_p=278629a4-108d-466d-8c1f-b029777318e7&pf_rd_r=N1GAYZZ833HPHYVNB7AH&pd_rd_wg=GiVUe&pd_rd_i=B0CW1HYDD3&ref_=dbs_r_recs_hcko_kmd_r_6&pd_rd_w=T30BE&content-id=amzn1.sym.278629a4-108d-466d-8c1f-b029777318e7&pd_rd_r=315b4212-0c7d-45e9-a66e-1916b6a3ad4a",
        "title": "Invention and Innovation　歴史に学ぶ「未来」のつくり方",
        "thumbnail": "https://m.media-amazon.com/images/I/31qk7s+EIgL._SY300_.jpg"
    },
    {
        "href": "https://www.amazon.co.jp/gp/product/B07RXV9QB7?storeType=ebooks&pf_rd_p=278629a4-108d-466d-8c1f-b029777318e7&pf_rd_r=N1GAYZZ833HPHYVNB7AH&pd_rd_wg=GiVUe&pd_rd_i=B07RXV9QB7&ref_=dbs_r_recs_hcko_kmd_r_7&pd_rd_w=T30BE&content-id=amzn1.sym.278629a4-108d-466d-8c1f-b029777318e7&pd_rd_r=315b4212-0c7d-45e9-a66e-1916b6a3ad4a",
        "title": "皇国の守護者（全）　１～９＋外伝集 (中公文庫)",
        "thumbnail": "https://m.media-amazon.com/images/I/51gGrXRv76L._SY300_.jpg"
    },
    {
        "href": "https://www.amazon.co.jp/gp/product/B00CZ584Y2?storeType=ebooks&pf_rd_p=278629a4-108d-466d-8c1f-b029777318e7&pf_rd_r=N1GAYZZ833HPHYVNB7AH&pd_rd_wg=GiVUe&pd_rd_i=B00CZ584Y2&ref_=dbs_r_recs_hcko_kmd_r_8&pd_rd_w=T30BE&content-id=amzn1.sym.278629a4-108d-466d-8c1f-b029777318e7&pd_rd_r=315b4212-0c7d-45e9-a66e-1916b6a3ad4a",
        "title": "諦める力～勝てないのは努力が足りないからじゃない",
        "thumbnail": "https://m.media-amazon.com/images/I/41Fkp6jbdZL._PJku-sticker-v7,TopRight,0,-50._SY300_.jpg"
    },
    {
        "href": "https://www.amazon.co.jp/gp/product/B0CMCZTYM2?storeType=ebooks&pf_rd_p=278629a4-108d-466d-8c1f-b029777318e7&pf_rd_r=N1GAYZZ833HPHYVNB7AH&pd_rd_wg=GiVUe&pd_rd_i=B0CMCZTYM2&ref_=dbs_r_recs_hcko_kmd_r_9&pd_rd_w=T30BE&content-id=amzn1.sym.278629a4-108d-466d-8c1f-b029777318e7&pd_rd_r=315b4212-0c7d-45e9-a66e-1916b6a3ad4a",
        "title": "その怪文書を読みましたか",
        "thumbnail": "https://m.media-amazon.com/images/I/41cRG0-pa8L._SY300_.jpg"
    },
    {
        "href": "https://www.amazon.co.jp/gp/product/B0C2YXHKJF?storeType=ebooks&pf_rd_p=278629a4-108d-466d-8c1f-b029777318e7&pf_rd_r=N1GAYZZ833HPHYVNB7AH&pd_rd_wg=GiVUe&pd_rd_i=B0C2YXHKJF&ref_=dbs_r_recs_hcko_kmd_r_10&pd_rd_w=T30BE&content-id=amzn1.sym.278629a4-108d-466d-8c1f-b029777318e7&pd_rd_r=315b4212-0c7d-45e9-a66e-1916b6a3ad4a",
        "title": "「スカイ・クロラ」シリーズ　全6巻合本版 (中公文庫)",
        "thumbnail": "https://m.media-amazon.com/images/I/51gQxXOcxgL._SY300_.jpg"
    },
    {
        "href": "https://www.amazon.co.jp/gp/product/B00UAAK07S?storeType=ebooks&pf_rd_p=278629a4-108d-466d-8c1f-b029777318e7&pf_rd_r=N1GAYZZ833HPHYVNB7AH&pd_rd_wg=GiVUe&pd_rd_i=B00UAAK07S&ref_=dbs_r_recs_hcko_kmd_r_11&pd_rd_w=T30BE&content-id=amzn1.sym.278629a4-108d-466d-8c1f-b029777318e7&pd_rd_r=315b4212-0c7d-45e9-a66e-1916b6a3ad4a",
        "title": "人工知能は人間を超えるか (角川ＥＰＵＢ選書)",
        "thumbnail": "https://m.media-amazon.com/images/I/51mWcqy+ipL._SY300_.jpg"
    },
    {
        "href": "https://www.amazon.co.jp/gp/product/B0CXMW59KJ?storeType=ebooks&pf_rd_p=278629a4-108d-466d-8c1f-b029777318e7&pf_rd_r=N1GAYZZ833HPHYVNB7AH&pd_rd_wg=GiVUe&pd_rd_i=B0CXMW59KJ&ref_=dbs_r_recs_hcko_kmd_r_12&pd_rd_w=T30BE&content-id=amzn1.sym.278629a4-108d-466d-8c1f-b029777318e7&pd_rd_r=315b4212-0c7d-45e9-a66e-1916b6a3ad4a",
        "title": "プログラマーの本気がExcelを覚醒させる 超絶Excel VBA",
        "thumbnail": "https://m.media-amazon.com/images/I/51GCJH+-HIL._SY300_.jpg"
    },
    {
        "href": "https://www.amazon.co.jp/gp/product/B07FW35F5R?storeType=ebooks&pf_rd_p=278629a4-108d-466d-8c1f-b029777318e7&pf_rd_r=N1GAYZZ833HPHYVNB7AH&pd_rd_wg=GiVUe&pd_rd_i=B07FW35F5R&ref_=dbs_r_recs_hcko_kmd_r_13&pd_rd_w=T30BE&content-id=amzn1.sym.278629a4-108d-466d-8c1f-b029777318e7&pd_rd_r=315b4212-0c7d-45e9-a66e-1916b6a3ad4a",
        "title": "けっきょく、よはく。余白を活かしたデザインレイアウトの本",
        "thumbnail": "https://m.media-amazon.com/images/I/417W8v2u5SL._SY300_.jpg"
    },
    {
        "href": "https://www.amazon.co.jp/gp/product/B08C2DF199?storeType=ebooks&pf_rd_p=278629a4-108d-466d-8c1f-b029777318e7&pf_rd_r=N1GAYZZ833HPHYVNB7AH&pd_rd_wg=GiVUe&pd_rd_i=B08C2DF199&ref_=dbs_r_recs_hcko_kmd_r_14&pd_rd_w=T30BE&content-id=amzn1.sym.278629a4-108d-466d-8c1f-b029777318e7&pd_rd_r=315b4212-0c7d-45e9-a66e-1916b6a3ad4a",
        "title": "トレース＆模写で学ぶ　デザインのドリル",
        "thumbnail": "https://m.media-amazon.com/images/I/51z+6TVq9eL._SY300_.jpg"
    },
    {
        "href": "https://www.amazon.co.jp/gp/product/B0CQJRQCVD?storeType=ebooks&pf_rd_p=278629a4-108d-466d-8c1f-b029777318e7&pf_rd_r=N1GAYZZ833HPHYVNB7AH&pd_rd_wg=GiVUe&pd_rd_i=B0CQJRQCVD&ref_=dbs_r_recs_hcko_kmd_r_15&pd_rd_w=T30BE&content-id=amzn1.sym.278629a4-108d-466d-8c1f-b029777318e7&pd_rd_r=315b4212-0c7d-45e9-a66e-1916b6a3ad4a",
        "title": "元・給食の先生がおしえるワンパン健康食堂",
        "thumbnail": "https://m.media-amazon.com/images/I/51Pw2OG+1sL._SY300_.jpg"
    },
    {
        "href": "https://www.amazon.co.jp/gp/product/B00BANJ84A?storeType=ebooks&pf_rd_p=278629a4-108d-466d-8c1f-b029777318e7&pf_rd_r=N1GAYZZ833HPHYVNB7AH&pd_rd_wg=GiVUe&pd_rd_i=B00BANJ84A&ref_=dbs_r_recs_hcko_kmd_r_16&pd_rd_w=T30BE&content-id=amzn1.sym.278629a4-108d-466d-8c1f-b029777318e7&pd_rd_r=315b4212-0c7d-45e9-a66e-1916b6a3ad4a",
        "title": "[新装版] 企業参謀 戦略的思考とは何か",
        "thumbnail": "https://m.media-amazon.com/images/I/51QuNeo2tlL._SY300_.jpg"
    },
    {
        "href": "https://www.amazon.co.jp/gp/product/B0B9GG56RM?storeType=ebooks&pf_rd_p=278629a4-108d-466d-8c1f-b029777318e7&pf_rd_r=N1GAYZZ833HPHYVNB7AH&pd_rd_wg=GiVUe&pd_rd_i=B0B9GG56RM&ref_=dbs_r_recs_hcko_kmd_r_17&pd_rd_w=T30BE&content-id=amzn1.sym.278629a4-108d-466d-8c1f-b029777318e7&pd_rd_r=315b4212-0c7d-45e9-a66e-1916b6a3ad4a",
        "title": "図解でわかる！　古武術式　疲れない体の使い方――「もっと合理的に、もっとラクに」動く",
        "thumbnail": "https://m.media-amazon.com/images/I/51H1qVCWLQL._SY300_.jpg"
    },
    {
        "href": "https://www.amazon.co.jp/gp/product/B0CVQ6J5BB?storeType=ebooks&pf_rd_p=278629a4-108d-466d-8c1f-b029777318e7&pf_rd_r=N1GAYZZ833HPHYVNB7AH&pd_rd_wg=GiVUe&pd_rd_i=B0CVQ6J5BB&ref_=dbs_r_recs_hcko_kmd_r_18&pd_rd_w=T30BE&content-id=amzn1.sym.278629a4-108d-466d-8c1f-b029777318e7&pd_rd_r=315b4212-0c7d-45e9-a66e-1916b6a3ad4a",
        "title": "IT'S ELEMENTAL さぁ、化学に目覚めよう 世界の見え方が変わる特別講義",
        "thumbnail": "https://m.media-amazon.com/images/I/417PUgLg06L._SY300_.jpg"
    },
    {
        "href": "https://www.amazon.co.jp/gp/product/B01JADEG6Q?storeType=ebooks&pf_rd_p=278629a4-108d-466d-8c1f-b029777318e7&pf_rd_r=N1GAYZZ833HPHYVNB7AH&pd_rd_wg=GiVUe&pd_rd_i=B01JADEG6Q&ref_=dbs_r_recs_hcko_kmd_r_19&pd_rd_w=T30BE&content-id=amzn1.sym.278629a4-108d-466d-8c1f-b029777318e7&pd_rd_r=315b4212-0c7d-45e9-a66e-1916b6a3ad4a",
        "title": "まんがでわかる 新渡戸稲造「武士道」―――剣は心なり(Business Comic Series) Business ComicSeries",
        "thumbnail": "https://m.media-amazon.com/images/I/51bYMwxxusL._PJku-sticker-v7,TopRight,0,-50._SY300_.jpg"
    }
]