[
    {
        "href": "https://www.amazon.co.jp/gp/product/B00DQ4SKM2?storeType=ebooks&pf_rd_p=7cef433f-789f-4bf6-bc14-7930610f4554&pf_rd_r=ZS0Z4ZWYNMNGZXE78THK&pd_rd_wg=E3v8j&pd_rd_i=B00DQ4SKM2&ref_=dbs_r_recs_hcko_kdd_r_0&pd_rd_w=wQnzn&content-id=amzn1.sym.7cef433f-789f-4bf6-bc14-7930610f4554&pd_rd_r=0b4cc2f8-ed86-4494-be83-53cfe61e7dd9",
        "title": "貧乏はお金持ち　「雇われない生き方」で格差社会を逆転する (講談社＋α文庫)",
        "thumbnail": "https://m.media-amazon.com/images/I/5183XyFReIL._SY300_.jpg"
    },
    {
        "href": "https://www.amazon.co.jp/gp/product/B07VX6DPRG?storeType=ebooks&pf_rd_p=7cef433f-789f-4bf6-bc14-7930610f4554&pf_rd_r=ZS0Z4ZWYNMNGZXE78THK&pd_rd_wg=E3v8j&pd_rd_i=B07VX6DPRG&ref_=dbs_r_recs_hcko_kdd_r_1&pd_rd_w=wQnzn&content-id=amzn1.sym.7cef433f-789f-4bf6-bc14-7930610f4554&pd_rd_r=0b4cc2f8-ed86-4494-be83-53cfe61e7dd9",
        "title": "地球の歩き方 A23 ポルトガル 2019-2020",
        "thumbnail": "https://m.media-amazon.com/images/I/51WE1uBaTPL._SY300_.jpg"
    },
    {
        "href": "https://www.amazon.co.jp/gp/product/B086R7ZZPV?storeType=ebooks&pf_rd_p=7cef433f-789f-4bf6-bc14-7930610f4554&pf_rd_r=ZS0Z4ZWYNMNGZXE78THK&pd_rd_wg=E3v8j&pd_rd_i=B086R7ZZPV&ref_=dbs_r_recs_hcko_kdd_r_2&pd_rd_w=wQnzn&content-id=amzn1.sym.7cef433f-789f-4bf6-bc14-7930610f4554&pd_rd_r=0b4cc2f8-ed86-4494-be83-53cfe61e7dd9",
        "title": "カレンの台所",
        "thumbnail": "https://m.media-amazon.com/images/I/413QlfkXd7L._SY300_.jpg"
    }
]