[
    {
        "href": "https://www.amazon.co.jp/-/en/gp/product/B0879Y54NX?storeType=ebooks&pageType=STOREFRONT&pf_rd_p=59105da2-0d96-492a-a35a-eb487464cfc3&pf_rd_r=2S66HA4AYMSE5WMCGK9A&pf_rd_s=merchandised-search-9&pf_rd_t=&ref_=dbs_f_r_shv_59105da2-0d96-492a-a35a-eb487464cfc3_0&pf_rd_i=3251934051",
        "title": "ズボラでもラクラク！１週間で脂肪肝はスッキリよくなる (三笠書房　電子書籍)",
        "thumbnail": "https://m.media-amazon.com/images/I/51yGgoioRmL._SY300_.jpg"
    },
    {
        "href": "https://www.amazon.co.jp/-/en/gp/product/B09M3G6M7Y?storeType=ebooks&pageType=STOREFRONT&pf_rd_p=59105da2-0d96-492a-a35a-eb487464cfc3&pf_rd_r=2S66HA4AYMSE5WMCGK9A&pf_rd_s=merchandised-search-9&pf_rd_t=&ref_=dbs_f_r_shv_59105da2-0d96-492a-a35a-eb487464cfc3_1&pf_rd_i=3251934051",
        "title": "最新 いまさら聞けないビットコインとブロックチェーン",
        "thumbnail": "https://m.media-amazon.com/images/I/51d+porZJBL._SY300_.jpg"
    },
    {
        "href": "https://www.amazon.co.jp/-/en/gp/product/B08NF6NLLG?storeType=ebooks&pageType=STOREFRONT&pf_rd_p=59105da2-0d96-492a-a35a-eb487464cfc3&pf_rd_r=2S66HA4AYMSE5WMCGK9A&pf_rd_s=merchandised-search-9&pf_rd_t=&ref_=dbs_f_r_shv_59105da2-0d96-492a-a35a-eb487464cfc3_2&pf_rd_i=3251934051",
        "title": "ＮＨＫ基礎英語　中学英語で読める　はじめての英語ライトノベル　異世界に転生したら伝説の少女だった件 音声DL BOOK",
        "thumbnail": "https://m.media-amazon.com/images/I/51UB1UZgeEL._SY300_.jpg"
    }
]