[
    {
        "href": "https://www.amazon.co.jp/gp/product/B01I55SZJE?storeType=ebooks&pf_rd_p=7cef433f-789f-4bf6-bc14-7930610f4554&pf_rd_r=XEBD1HPE6BMBZPJ7BH5V&pd_rd_wg=mvxdf&pd_rd_i=B01I55SZJE&ref_=dbs_r_recs_hcko_kdd_r_0&pd_rd_w=p9eCF&content-id=amzn1.sym.7cef433f-789f-4bf6-bc14-7930610f4554&pd_rd_r=df7f0d94-bda4-4763-bb43-82e57c436cdd",
        "title": "ヒトはなぜ先延ばしをしてしまうのか",
        "thumbnail": "https://m.media-amazon.com/images/I/51bHVYHcEmL._SY300_.jpg"
    },
    {
        "href": "https://www.amazon.co.jp/gp/product/B09S67KLYN?storeType=ebooks&pf_rd_p=7cef433f-789f-4bf6-bc14-7930610f4554&pf_rd_r=XEBD1HPE6BMBZPJ7BH5V&pd_rd_wg=mvxdf&pd_rd_i=B09S67KLYN&ref_=dbs_r_recs_hcko_kdd_r_1&pd_rd_w=p9eCF&content-id=amzn1.sym.7cef433f-789f-4bf6-bc14-7930610f4554&pd_rd_r=df7f0d94-bda4-4763-bb43-82e57c436cdd",
        "title": "経営リーダーのための社会システム論～構造的問題と僕らの未来～",
        "thumbnail": "https://m.media-amazon.com/images/I/41AcfXjYZqL._SY300_.jpg"
    },
    {
        "href": "https://www.amazon.co.jp/gp/product/B0CH7XD2BD?storeType=ebooks&pf_rd_p=7cef433f-789f-4bf6-bc14-7930610f4554&pf_rd_r=XEBD1HPE6BMBZPJ7BH5V&pd_rd_wg=mvxdf&pd_rd_i=B0CH7XD2BD&ref_=dbs_r_recs_hcko_kdd_r_2&pd_rd_w=p9eCF&content-id=amzn1.sym.7cef433f-789f-4bf6-bc14-7930610f4554&pd_rd_r=df7f0d94-bda4-4763-bb43-82e57c436cdd",
        "title": "最高のコーチになるためのスポーツコーチング学 ―知っておくべき「フレームワーク」と「スキル」―",
        "thumbnail": "https://m.media-amazon.com/images/I/51MnLOrClbL._SY300_.jpg"
    }
]