[
    {
        "href": "https://www.amazon.co.jp/-/en/gp/product/B0B33X96JD?storeType=ebooks&pf_rd_t=&pd_rd_i=B0B33X96JD&content-id=amzn1.sym.f3dea059-c12b-4f25-8a1b-c6df02f7d162&pageType=STOREFRONT&pf_rd_p=f3dea059-c12b-4f25-8a1b-c6df02f7d162&pf_rd_r=00QXV6C3ENVFQBBXC5CM&pd_rd_wg=v5qtX&pf_rd_s=merchandised-search-11&ref_=dbs_f_r_shv_hcko_kdd_e22eff8d-f530-45e0-9860-4ea881aaffea_0&pd_rd_w=VGNY9&pf_rd_i=3251934051&pd_rd_r=756077fc-7599-406c-8001-51623b59f64f",
        "title": "素人はボロ儲けを狙うのはおやめなさい 安心・安全・確実な投資の教科書 (扶桑社ＢＯＯＫＳ)",
        "thumbnail": "https://m.media-amazon.com/images/I/51S9RhLv6iL._SY375_.jpg"
    },
    {
        "href": "https://www.amazon.co.jp/-/en/gp/product/B08XQWNZVP?storeType=ebooks&pf_rd_t=&pd_rd_i=B08XQWNZVP&content-id=amzn1.sym.f3dea059-c12b-4f25-8a1b-c6df02f7d162&pageType=STOREFRONT&pf_rd_p=f3dea059-c12b-4f25-8a1b-c6df02f7d162&pf_rd_r=00QXV6C3ENVFQBBXC5CM&pd_rd_wg=v5qtX&pf_rd_s=merchandised-search-11&ref_=dbs_f_r_shv_hcko_kdd_e22eff8d-f530-45e0-9860-4ea881aaffea_1&pd_rd_w=VGNY9&pf_rd_i=3251934051&pd_rd_r=756077fc-7599-406c-8001-51623b59f64f",
        "title": "子どもが不登校になったら読む本 ——すべて解決できる〝笑顔の処方箋〟",
        "thumbnail": "https://m.media-amazon.com/images/I/51UNhPvJHrL._SY375_.jpg"
    },
    {
        "href": "https://www.amazon.co.jp/-/en/gp/product/B09HGYN6TR?storeType=ebooks&pf_rd_t=&pd_rd_i=B09HGYN6TR&content-id=amzn1.sym.f3dea059-c12b-4f25-8a1b-c6df02f7d162&pageType=STOREFRONT&pf_rd_p=f3dea059-c12b-4f25-8a1b-c6df02f7d162&pf_rd_r=00QXV6C3ENVFQBBXC5CM&pd_rd_wg=v5qtX&pf_rd_s=merchandised-search-11&ref_=dbs_f_r_shv_hcko_kdd_e22eff8d-f530-45e0-9860-4ea881aaffea_2&pd_rd_w=VGNY9&pf_rd_i=3251934051&pd_rd_r=756077fc-7599-406c-8001-51623b59f64f",
        "title": "データ分析実務スキル検定 公式テキスト",
        "thumbnail": "https://m.media-amazon.com/images/I/516+SQMLDZL._SY375_.jpg"
    }
]